hack_chatgpt/__init__.py
hack_chatgpt/client/__init__.py
hack_chatgpt/client/client.py
hack_chatgpt/generated/proto/chatgpt_pb2.py
hack_chatgpt/generated/proto/chatgpt_pb2_grpc.py
hack_chatgpt-0.1.1.dist-info/LICENSE
hack_chatgpt-0.1.1.dist-info/WHEEL
hack_chatgpt-0.1.1.dist-info/METADATA
hack_chatgpt-0.1.1.dist-info/RECORD
