Metadata-Version: 2.1
Name: hack-chatgpt
Version: 0.1.1
Summary: 
License: MIT
Author: ybyang
Author-email: ybyang7@iflytek.com
Requires-Python: >=3.7,<4.0
Classifier: License :: OSI Approved :: MIT License
Classifier: Programming Language :: Python :: 3
Classifier: Programming Language :: Python :: 3.10
Classifier: Programming Language :: Python :: 3.7
Classifier: Programming Language :: Python :: 3.8
Classifier: Programming Language :: Python :: 3.9
Requires-Dist: flask_restx (>=1.0.0)
Requires-Dist: grpcio (>=1.50.0)
Requires-Dist: grpcio-health-checking (>=1.50.0)
Requires-Dist: grpcio-tools (>=1.50.0)
Requires-Dist: jinja2 (>=2.0)
Requires-Dist: jsonref (>=1.0.0)
Requires-Dist: plumbum (>=1.7.0)
Requires-Dist: protobuf (>=4.21)
Requires-Dist: pydantic (>=1.8)
